{
    "message_buffer_second": 1,
    "debug": 0,

    "model": "dify",

    "dify_api_base": "http://localhost/v1",
    "dify_api_key": "",
    "dify_app_type": "chatbot",

    "coze_api_base": "",
    "coze_api_key": "",
    "coze_bot_id": "",

    "channel_type": "sikulix",

    "gewechat_app_id": "",
    "gewechat_base_url": "http://192.168.29.237:2531/v2/api",
    "gewechat_callback_url": "http://192.168.29.237:9919/v2/api/callback/collect",
    "gewechat_download_url": "http://192.168.29.237:2532/download",
    "gewechat_token": "",
    "nick_name_black_list": [],
    "wxid_black_list": [],
    "wxid_recip_note": ""
}